Metadata-Version: 1.0
Name: marve
Version: 0.0.7
Summary: Package for extracting measurements and related entities from text.
Home-page: https://github.com/khundman/marve
Author: Kyle Hundman
Author-email: khundman@gmail.com
License:                                  Apache License
